shakenfist_client/__init__.py
shakenfist_client/_version.py
shakenfist_client/apiclient.py
shakenfist_client/main.py
shakenfist_client/util.py
shakenfist_client/ansible/sf_instance
shakenfist_client/ansible/sf_namespace
shakenfist_client/ansible/sf_network
shakenfist_client/ansible/sf_snapshot.py
shakenfist_client/commandline/admin.py
shakenfist_client/commandline/ansible.py
shakenfist_client/commandline/artifact.py
shakenfist_client/commandline/backup.py
shakenfist_client/commandline/blob.py
shakenfist_client/commandline/instance.py
shakenfist_client/commandline/interface.py
shakenfist_client/commandline/label.py
shakenfist_client/commandline/namespace.py
shakenfist_client/commandline/network.py
shakenfist_client/commandline/node.py
shakenfist_client/tests/__init__.py
shakenfist_client/tests/test_client_apiclient.py
shakenfist_client-0.8.1.dist-info/licenses/AUTHORS
shakenfist_client-0.8.1.dist-info/licenses/LICENSE
shakenfist_client-0.8.1.dist-info/METADATA
shakenfist_client-0.8.1.dist-info/WHEEL
shakenfist_client-0.8.1.dist-info/entry_points.txt
shakenfist_client-0.8.1.dist-info/top_level.txt
shakenfist_client-0.8.1.dist-info/RECORD
